alignak_checks_mysql/__init__.py
alignak_checks_mysql-1.2.2.data/data/share/alignak/etc/arbiter/packs/mysql/commands.cfg
alignak_checks_mysql-1.2.2.data/data/share/alignak/etc/arbiter/packs/mysql/groups.cfg
alignak_checks_mysql-1.2.2.data/data/share/alignak/etc/arbiter/packs/mysql/services.cfg
alignak_checks_mysql-1.2.2.data/data/share/alignak/etc/arbiter/packs/mysql/templates.cfg
alignak_checks_mysql-1.2.2.data/data/share/alignak/etc/arbiter/packs/resource.d/mysql.cfg
alignak_checks_mysql-1.2.2.data/data/share/alignak/etc/backend-json/mysql/commands.json
alignak_checks_mysql-1.2.2.data/data/share/alignak/etc/backend-json/mysql/hostgroups.json
alignak_checks_mysql-1.2.2.data/data/share/alignak/etc/backend-json/mysql/hosts-templates.json
alignak_checks_mysql-1.2.2.data/data/share/alignak/etc/backend-json/mysql/servicegroups.json
alignak_checks_mysql-1.2.2.data/data/share/alignak/etc/backend-json/mysql/services-templates.json
alignak_checks_mysql-1.2.2.data/data/share/alignak/etc/backend-json/mysql/setup.sh
alignak_checks_mysql-1.2.2.data/data/share/alignak/libexec/check_mysql_health
alignak_checks_mysql-1.2.2.dist-info/LICENSE
alignak_checks_mysql-1.2.2.dist-info/METADATA
alignak_checks_mysql-1.2.2.dist-info/WHEEL
alignak_checks_mysql-1.2.2.dist-info/top_level.txt
alignak_checks_mysql-1.2.2.dist-info/RECORD
